filesignaturecollectors/__init__.py
filesignaturecollectors/cli.py
filesignaturecollectors/controller.py
filesignaturecollectors/get_data_from_gck.py
filesignaturecollectors/get_data_from_wiki.py
filesignaturecollectors/models.py
filesignaturecollectors/to_file.py
filesignaturecollectors/to_sqlite3.py
filesignaturecollectors/utils/__init__.py
filesignaturecollectors/utils/listfilemagicdata.py
filesignaturecollectors/utils/store_data.py
filesignaturecollectors-0.1.7.dist-info/METADATA
filesignaturecollectors-0.1.7.dist-info/WHEEL
filesignaturecollectors-0.1.7.dist-info/entry_points.txt
filesignaturecollectors-0.1.7.dist-info/RECORD
