Metadata-Version: 2.1
Name: filesignaturecollectors
Version: 0.1.7
Summary: Collects, processes and stores information on 'magic numbers'.
Home-page: https://github.com/kurotom/filesignaturecollectors
License: GPL-3.0-or-later
Keywords: filesignature,file signature,magicnumbers,magic numbers
Author: kurotom
Author-email: 55354389+kurotom@users.noreply.github.com
Requires-Python: >=3.7,<4.0
Classifier: License :: OSI Approved :: GNU General Public License v3 or later (GPLv3+)
Classifier: Programming Language :: Python :: 3
Classifier: Programming Language :: Python :: 3.7
Classifier: Programming Language :: Python :: 3.8
Classifier: Programming Language :: Python :: 3.9
Classifier: Programming Language :: Python :: 3.10
Classifier: Programming Language :: Python :: 3.11
Classifier: Topic :: File Formats
Requires-Dist: beautifulsoup4 (>=4.12.3,<5.0.0)
Requires-Dist: requests (>=2.31.0,<3.0.0)
Project-URL: Bug Tracker, https://github.com/kurotom/filesignaturecollectors/issues
Project-URL: Pypi, https://pypi.org/project/filesignaturecollectors/
Project-URL: Repository, https://github.com/kurotom/filesignaturecollectors
